MANIFEST.in
README.rst
ez_setup.py
js2model
js2model.py
setup.py
js2model.egg-info/PKG-INFO
js2model.egg-info/SOURCES.txt
js2model.egg-info/dependency_links.txt
js2model.egg-info/not-zip-safe
js2model.egg-info/requires.txt
js2model.egg-info/top_level.txt
tr/__init__.py
tr/jsonschema/__init__.py
tr/jsonschema/jsonschema2model.py
tr/jsonschema/templates_cpp/base.mako
tr/jsonschema/templates_cpp/class.cpp.mako
tr/jsonschema/templates_cpp/class.h.mako
tr/jsonschema/templates_cpp/enum.h.mako
tr/jsonschema/templates_cpp/models.h.mako
tr/jsonschema/templates_cpp/dependencies/rapidjson/allocators.h
tr/jsonschema/templates_cpp/dependencies/rapidjson/document.h
tr/jsonschema/templates_cpp/dependencies/rapidjson/encodedstream.h
tr/jsonschema/templates_cpp/dependencies/rapidjson/encodings.h
tr/jsonschema/templates_cpp/dependencies/rapidjson/filereadstream.h
tr/jsonschema/templates_cpp/dependencies/rapidjson/filestream.h
tr/jsonschema/templates_cpp/dependencies/rapidjson/filewritestream.h
tr/jsonschema/templates_cpp/dependencies/rapidjson/memorybuffer.h
tr/jsonschema/templates_cpp/dependencies/rapidjson/memorystream.h
tr/jsonschema/templates_cpp/dependencies/rapidjson/prettywriter.h
tr/jsonschema/templates_cpp/dependencies/rapidjson/rapidjson.h
tr/jsonschema/templates_cpp/dependencies/rapidjson/reader.h
tr/jsonschema/templates_cpp/dependencies/rapidjson/stringbuffer.h
tr/jsonschema/templates_cpp/dependencies/rapidjson/writer.h
tr/jsonschema/templates_cpp/dependencies/rapidjson/error/en.h
tr/jsonschema/templates_cpp/dependencies/rapidjson/error/error.h
tr/jsonschema/templates_cpp/dependencies/rapidjson/internal/biginteger.h
tr/jsonschema/templates_cpp/dependencies/rapidjson/internal/diyfp.h
tr/jsonschema/templates_cpp/dependencies/rapidjson/internal/dtoa.h
tr/jsonschema/templates_cpp/dependencies/rapidjson/internal/ieee754.h
tr/jsonschema/templates_cpp/dependencies/rapidjson/internal/itoa.h
tr/jsonschema/templates_cpp/dependencies/rapidjson/internal/meta.h
tr/jsonschema/templates_cpp/dependencies/rapidjson/internal/pow10.h
tr/jsonschema/templates_cpp/dependencies/rapidjson/internal/stack.h
tr/jsonschema/templates_cpp/dependencies/rapidjson/internal/strfunc.h
