Metadata-Version: 1.1
Name: js2model
Version: 0.2.dev11
Summary: Auto-generate plain old object models + custom JSON serialization/deserialization code from JSON schema definitions.
Home-page: https://github.com/thomsonreuters/js2model
Author: Kevin Zimmerman
Author-email: kevin.zimmerman@thomsonreuters.com
License: BSD
Keywords: json,schema,jsonschema,json-schema,json schema,json object,generate,generator,builder,draft 4
Platform: any
Classifier: Development Status :: 4 - Beta
Classifier: Intended Audience :: Developers
Classifier: License :: OSI Approved :: BSD License
Classifier: Natural Language :: English
Classifier: Operating System :: OS Independent
Classifier: Programming Language :: Python
Classifier: Programming Language :: Python :: 2
Classifier: Programming Language :: Python :: 2.7
Classifier: Programming Language :: Python :: 3
Classifier: Programming Language :: Python :: 3.4
Classifier: Topic :: Software Development :: Libraries :: Python Modules
Classifier: Topic :: Utilities
